orbis_plugin_storage_html_pages/__init__.py
orbis_plugin_storage_html_pages/build_html.py
orbis_plugin_storage_html_pages/libs.py
orbis_plugin_storage_html_pages/main.py
orbis_plugin_storage_html_pages/templates/__init__.py
orbis_plugin_storage_html_pages/templates/css_bootstrap.py
orbis_plugin_storage_html_pages/templates/css_color.py
orbis_plugin_storage_html_pages/templates/css_dropdown.py
orbis_plugin_storage_html_pages/templates/css_html.py
orbis_plugin_storage_html_pages/templates/css_text_container.py
orbis_plugin_storage_html_pages/templates/gold_corpus.py
orbis_plugin_storage_html_pages/templates/gold_entities.py
orbis_plugin_storage_html_pages/templates/html_body.py
orbis_plugin_storage_html_pages/templates/item_header.py
orbis_plugin_storage_html_pages/templates/js_arrow_key_navigation.py
orbis_plugin_storage_html_pages/templates/js_bootstrap.py
orbis_plugin_storage_html_pages/templates/js_color.py
orbis_plugin_storage_html_pages/templates/js_dropdown.py
orbis_plugin_storage_html_pages/templates/js_navigation.py
orbis_plugin_storage_html_pages/templates/js_popper.py
orbis_plugin_storage_html_pages/templates/navigation.py
orbis_plugin_storage_html_pages/templates/orbis_header.py
orbis_plugin_storage_html_pages/templates/predicted_corpus.py
orbis_plugin_storage_html_pages/templates/predicted_entities.py
orbis_plugin_storage_html_pages-2.3.1.dist-info/LICENSE
orbis_plugin_storage_html_pages-2.3.1.dist-info/METADATA
orbis_plugin_storage_html_pages-2.3.1.dist-info/WHEEL
orbis_plugin_storage_html_pages-2.3.1.dist-info/top_level.txt
orbis_plugin_storage_html_pages-2.3.1.dist-info/RECORD
