Metadata-Version: 2.1
Name: orbis-plugin-storage-html-pages
Version: 2.3.1
Summary: The html_pages storage plugin for Orbis
Home-page: https://github.com/orbis-eval/orbis_plugin_storage_html_pages
Author: fabod, Roger Waldvogel
License: GPL2
Platform: UNKNOWN
Requires-Python: >3.6
Requires-Dist: palettable (==3.1.1)
Requires-Dist: inscriptis (==1.1.2)
